discord/ext/science/__init__.py
discord/ext/science/client.py
discord/ext/science/config.py
discord/ext/science/flags.py
discord/ext/science/gateway.py
discord/ext/science/op.py
discord/ext/science/snooper.py
discord/ext/science/snoopy.py
discord/ext/science/recorders/base.py
discord/ext/science/recorders/databases.py
discord_ext_science-0.2.0.dist-info/LICENSE
discord_ext_science-0.2.0.dist-info/METADATA
discord_ext_science-0.2.0.dist-info/WHEEL
discord_ext_science-0.2.0.dist-info/top_level.txt
discord_ext_science-0.2.0.dist-info/RECORD
