Metadata-Version: 2.1
Name: discord-ext-science
Version: 0.2.0
Summary: A simple event logger for discord.py.
Home-page: https://github.com/NCPlayz/discord-ext-science
Author: NCPlayz
License: MIT
Platform: UNKNOWN
Classifier: License :: OSI Approved :: MIT License
Classifier: Intended Audience :: Developers
Classifier: Natural Language :: English
Classifier: Operating System :: OS Independent
Classifier: Programming Language :: Python :: 3.8
Classifier: Programming Language :: Python :: 3.7
Classifier: Topic :: Internet
Classifier: Topic :: Software Development :: Libraries
Classifier: Topic :: Software Development :: Libraries :: Python Modules
Classifier: Topic :: Utilities
Requires-Python: >=3.7.0
Requires-Dist: discord.py (==1.3.3)
Provides-Extra: databases
Requires-Dist: databases ; extra == 'databases'
